{
  "metadata": {
    "systemInfo": {
      "pageViewport": {
        "width": 800,
        "height": 600
      },
      "userAgent": "Mozilla/5.0 (Macintosh; Intel Mac OS X 10_15_4) AppleWebKit/537.36 (KHTML, like Gecko) HeadlessChrome/76.0.3803.0 Safari/537.36",
      "browserVersion": "HeadlessChrome/76.0.3803.0",
      "modelName": "MacBookPro",
      "modelVersion": "11.3",
      "browserPlatform": "MacIntel"
    }
  },
  "steps": [
    {
      "index": 1,
      "startTimestamp": 1591218997587,
      "screenshot": "1.page-goto.png",
      "consoleEntries": [
        {
          "level": "log",
          "text": "Injected log for:  goto",
          "line": 3,
          "column": 24,
          "url": "__puppeteer_evaluation_script__",
          "timestamp": 1591218997611
        },
        {
          "level": "info",
          "text": "%cDownload the React DevTools for a better development experience: https://fb.me/react-devtools font-weight:bold",
          "line": 21257,
          "column": 16,
          "url": "webpack-internal:///./node_modules/react-dom/cjs/react-dom.development.js",
          "timestamp": 1591218998148
        },
        {
          "level": "warning",
          "text": "@fluentui/react-northstar: CSSinJS Debug data collection is disabled. To enable data collection paste `window.localStorage.fluentUIDebug = true` to your browser console and reload the page.",
          "line": 16,
          "column": 18,
          "url": "webpack-internal:///./packages/fluentui/styles/src/debugEnabled.ts",
          "timestamp": 1591218998174
        },
        {
          "level": "warning",
          "text": "@fluentui/react-northstar: You are running Fela in production mode. This limits your ability to edit styles in browsers development tools. To enable development mode please paste `window.localStorage.felaDevMode = true` to your browsers console and reload the page.",
          "line": 40,
          "column": 12,
          "url": "webpack-internal:///./packages/fluentui/react-northstar/src/utils/felaRenderer.tsx",
          "timestamp": 1591218998231
        }
      ],
      "unhandledExceptions": [
        {
          "message": "Error: Injected error for: goto\n    at __puppeteer_evaluation_script__:3:23",
          "timestamp": 1591218997624
        }
      ],
      "fnName": "goto",
      "text": "http://localhost:8082/toolbar-menu-overflow-wrapped",
      "endTimestamp": 1591218998558,
      "name": "goto \"http://localhost:8082/toolbar-menu-overflow-wrapped\""
    },
    {
      "index": 2,
      "startTimestamp": 1591218998559,
      "rect": {
        "x": 0,
        "y": 0,
        "width": 800,
        "height": 32,
        "top": 0,
        "right": 800,
        "bottom": 32,
        "left": 0,
        "screenWidth": 800,
        "screenHeight": 600,
        "devicePixelRatio": 1
      },
      "screenshot": "2.page-waitForSelector.png",
      "consoleEntries": [
        {
          "level": "log",
          "text": "Injected log for:  waitForSelector",
          "line": 3,
          "column": 24,
          "url": "__puppeteer_evaluation_script__",
          "timestamp": 1591218998582
        }
      ],
      "unhandledExceptions": [
        {
          "message": "Error: Injected error for: waitForSelector\n    at __puppeteer_evaluation_script__:3:23",
          "timestamp": 1591218998594
        }
      ],
      "selector": ".ui-toolbar",
      "fnName": "waitForSelector",
      "endTimestamp": 1591218998928,
      "name": "waitForSelector \".ui-toolbar\""
    },
    {
      "index": 3,
      "startTimestamp": 1591218998929,
      "rect": {
        "x": 363.078125,
        "y": 0,
        "width": 32,
        "height": 32,
        "top": 0,
        "right": 395.078125,
        "bottom": 32,
        "left": 363.078125,
        "screenWidth": 800,
        "screenHeight": 600,
        "devicePixelRatio": 1
      },
      "screenshot": "3.page-waitForSelector.png",
      "consoleEntries": [
        {
          "level": "log",
          "text": "Injected log for:  waitForSelector",
          "line": 3,
          "column": 24,
          "url": "__puppeteer_evaluation_script__",
          "timestamp": 1591218998953
        }
      ],
      "unhandledExceptions": [
        {
          "message": "Error: Injected error for: waitForSelector\n    at __puppeteer_evaluation_script__:3:23",
          "timestamp": 1591218998964
        }
      ],
      "selector": ".ui-toolbar__itemwrapper:nth-child(11) .ui-toolbar__item",
      "fnName": "waitForSelector",
      "endTimestamp": 1591218999296,
      "name": "waitForSelector \".ui-toolbar__itemwrapper:nth-child(11) .ui-toolbar__item\""
    },
    {
      "index": 4,
      "startTimestamp": 1591218999345,
      "screenshot": "4.page-evaluate.png",
      "consoleEntries": [
        {
          "level": "log",
          "text": "Injected log for:  evaluate",
          "line": 3,
          "column": 24,
          "url": "__puppeteer_evaluation_script__",
          "timestamp": 1591218999369
        }
      ],
      "unhandledExceptions": [
        {
          "message": "Error: Injected error for: evaluate\n    at __puppeteer_evaluation_script__:3:23",
          "timestamp": 1591218999386
        }
      ],
      "fnName": "evaluate",
      "endTimestamp": 1591218999645,
      "name": "evaluate"
    },
    {
      "index": 6,
      "startTimestamp": 1591218999646,
      "screenshot": "6.page-viewport.png",
      "consoleEntries": [
        {
          "level": "log",
          "text": "Injected log for:  viewport",
          "line": 3,
          "column": 24,
          "url": "__puppeteer_evaluation_script__",
          "timestamp": 1591218999669
        },
        {
          "level": "log",
          "text": "Injected log for:  setViewport",
          "line": 3,
          "column": 24,
          "url": "__puppeteer_evaluation_script__",
          "timestamp": 1591218999670
        }
      ],
      "unhandledExceptions": [
        {
          "message": "Error: Injected error for: viewport\n    at __puppeteer_evaluation_script__:3:23",
          "timestamp": 1591218999684
        },
        {
          "message": "Error: Injected error for: setViewport\n    at __puppeteer_evaluation_script__:3:23",
          "timestamp": 1591218999685
        }
      ],
      "fnName": "viewport",
      "endTimestamp": 1591218999917,
      "name": "viewport"
    },
    {
      "index": 8,
      "startTimestamp": 1591219000177,
      "screenshot": "8.page-viewport.png",
      "consoleEntries": [
        {
          "level": "log",
          "text": "Injected log for:  viewport",
          "line": 3,
          "column": 24,
          "url": "__puppeteer_evaluation_script__",
          "timestamp": 1591219000200
        },
        {
          "level": "log",
          "text": "Injected log for:  setViewport",
          "line": 3,
          "column": 24,
          "url": "__puppeteer_evaluation_script__",
          "timestamp": 1591219000200
        }
      ],
      "unhandledExceptions": [
        {
          "message": "Error: Injected error for: viewport\n    at __puppeteer_evaluation_script__:3:23",
          "timestamp": 1591219000213
        },
        {
          "message": "Error: Injected error for: setViewport\n    at __puppeteer_evaluation_script__:3:23",
          "timestamp": 1591219000213
        }
      ],
      "fnName": "viewport",
      "endTimestamp": 1591219000449,
      "name": "viewport"
    }
  ]
}